rez_proxy/__init__.py
rez_proxy/cli.py
rez_proxy/config.py
rez_proxy/exceptions.py
rez_proxy/main.py
rez_proxy/core/__init__.py
rez_proxy/core/context.py
rez_proxy/core/platform.py
rez_proxy/core/rez_config.py
rez_proxy/middleware/__init__.py
rez_proxy/middleware/context.py
rez_proxy/models/__init__.py
rez_proxy/models/schemas.py
rez_proxy/routers/__init__.py
rez_proxy/routers/build.py
rez_proxy/routers/environments.py
rez_proxy/routers/package_ops.py
rez_proxy/routers/packages.py
rez_proxy/routers/repositories.py
rez_proxy/routers/resolver.py
rez_proxy/routers/rez_config.py
rez_proxy/routers/shells.py
rez_proxy/routers/suites.py
rez_proxy/routers/system.py
rez_proxy/routers/versions.py
rez_proxy/utils/__init__.py
rez_proxy/utils/rez_detector.py
rez_proxy-1.2.0.dist-info/licenses/LICENSE
rez_proxy-1.2.0.dist-info/METADATA
rez_proxy-1.2.0.dist-info/WHEEL
rez_proxy-1.2.0.dist-info/entry_points.txt
rez_proxy-1.2.0.dist-info/top_level.txt
rez_proxy-1.2.0.dist-info/RECORD
