Metadata-Version: 2.4
Name: rez-proxy
Version: 1.2.0
Summary: RESTful API proxy for Rez package manager
Author-email: Hal <hal.long@outlook.com>
License-Expression: MIT
Project-URL: Homepage, https://github.com/loonghao/rez-proxy
Project-URL: Documentation, https://github.com/loonghao/rez-proxy#readme
Project-URL: Repository, https://github.com/loonghao/rez-proxy.git
Project-URL: Issues, https://github.com/loonghao/rez-proxy/issues
Classifier: Development Status :: 4 - Beta
Classifier: Intended Audience :: Developers
Classifier: Programming Language :: Python :: 3
Classifier: Programming Language :: Python :: 3.10
Classifier: Programming Language :: Python :: 3.11
Classifier: Programming Language :: Python :: 3.12
Classifier: Programming Language :: Python :: 3.13
Requires-Python: >=3.10
License-File: LICENSE
Requires-Dist: fastapi>=0.100.0
Requires-Dist: uvicorn[standard]>=0.34.0
Requires-Dist: pydantic>=2.11.0
Requires-Dist: pydantic-settings>=2.9.0
Requires-Dist: click>=8.2.1
Requires-Dist: python-multipart>=0.0.6
Requires-Dist: fastapi-versioning>=0.10.0
Requires-Dist: rez
Provides-Extra: dev
Requires-Dist: pytest>=8.4.0; extra == "dev"
Requires-Dist: pytest-asyncio>=0.21.0; extra == "dev"
Requires-Dist: pytest-cov>=4.0.0; extra == "dev"
Requires-Dist: httpx>=0.24.0; extra == "dev"
Requires-Dist: ruff>=0.1.0; extra == "dev"
Requires-Dist: mypy>=1.16.0; extra == "dev"
Requires-Dist: pyfakefs>=5.0.0; extra == "dev"
Requires-Dist: commitizen>=3.0.0; extra == "dev"
Dynamic: license-file
